skill_test.py
skill_test-0.4.0.dist-info/WHEEL
skill_test-0.4.0.dist-info/METADATA
skill_test-0.4.0.dist-info/RECORD
