Metadata-Version: 2.1
Name: skill-test
Version: 0.4.0
Summary: 
Author: fridayy
Author-email: benjamin.krenn@leftshift.one
Requires-Python: >=3.6,<4.0
Classifier: Programming Language :: Python :: 3
Classifier: Programming Language :: Python :: 3.6
Classifier: Programming Language :: Python :: 3.7
Classifier: Programming Language :: Python :: 3.8
Requires-Dist: dynabuffers (==0.23.0)
Requires-Dist: interstate-py (==1.1.6)
Requires-Dist: pyyaml (>=5.3.1,<6.0.0)
